bookcommit.py
setup.py
bookcommit.egg-info/PKG-INFO
bookcommit.egg-info/SOURCES.txt
bookcommit.egg-info/dependency_links.txt
bookcommit.egg-info/top_level.txt
bookcommit.egg-info/zip-safe