Metadata-Version: 1.0
Name: bookcommit
Version: 1.0
Summary: Mercurial extension to automatically prepend the current bookmark name to the commit message.
Home-page: http://github.com/grimborg/bookcommit
Author: Oscar Vilaplana
Author-email: dev@oscarvilaplana.cat
License: GPLv2
Download-URL: http://pypi.python.org/pypi/bookcommit
Keywords: mercurial hg scm
Platform: UNKNOWN
